aopy/__init__.py
aopy-0.0.3.dist-info/LICENSE
aopy-0.0.3.dist-info/METADATA
aopy-0.0.3.dist-info/WHEEL
aopy-0.0.3.dist-info/top_level.txt
aopy-0.0.3.dist-info/RECORD
