Metadata-Version: 2.1
Name: aopy
Version: 0.0.3
Summary: Unofficial tool for interacting with the Art of Problem Solving website.
Home-page: https://gitlab.com/epiccakeking/aopy
Author: epiccakeking
Author-email: epiccakeking@gmail.com
License: UNKNOWN
Project-URL: Bug Tracker, https://gitlab.com/epiccakeking/aopy/-/issues
Platform: UNKNOWN
Classifier: Programming Language :: Python :: 3
Classifier: License :: OSI Approved :: MIT License
Classifier: Operating System :: OS Independent
Requires-Python: >=3.6
License-File: LICENSE
